wonderful_bing/__init__.py
wonderful_bing/wonderful_bing.py
wonderful_bing/img/icon.png
wonderful_bing/img/notify.jpg
wonderful_bing/img/notify.png
wonderful_bing-0.10.0.dist-info/LICENSE
wonderful_bing-0.10.0.dist-info/METADATA
wonderful_bing-0.10.0.dist-info/WHEEL
wonderful_bing-0.10.0.dist-info/entry_points.txt
wonderful_bing-0.10.0.dist-info/top_level.txt
wonderful_bing-0.10.0.dist-info/RECORD
