Metadata-Version: 2.1
Name: wonderful-bing
Version: 0.10.0
Summary: A script download Bing's img and set as wallpaper
Home-page: https://github.com/lord63/wonderful_bing
Author: lord63
Author-email: lord63.j@gmail.com
License: MIT
Keywords: bing wallpaper
Platform: UNKNOWN
Classifier: Development Status :: 4 - Beta
Classifier: Operating System :: POSIX
Classifier: Operating System :: POSIX :: Linux
Classifier: License :: OSI Approved :: MIT License
Classifier: Programming Language :: Python :: 2
Classifier: Programming Language :: Python :: 2.7
Classifier: Programming Language :: Python :: 3
Classifier: Programming Language :: Python :: 3.5
Classifier: Programming Language :: Python :: 3.6
Classifier: Programming Language :: Python :: 3.7
Classifier: Programming Language :: Python :: 3.8
Requires-Dist: docopt (>=0.6.2)
Requires-Dist: requests (>=2.4.0)
